LICENSE
README.md
pyproject.toml
src/kepmodel/__init__.py
src/kepmodel/astro.py
src/kepmodel/astrorv.py
src/kepmodel/rv.py
src/kepmodel/timeseries.py
src/kepmodel/tools.py
src/kepmodel.egg-info/PKG-INFO
src/kepmodel.egg-info/SOURCES.txt
src/kepmodel.egg-info/dependency_links.txt
src/kepmodel.egg-info/requires.txt
src/kepmodel.egg-info/top_level.txt
tests/test_astromodel.py
tests/test_astrorvmodel.py
tests/test_rvmodel.py