Metadata-Version: 2.1
Name: kepmodel
Version: 1.0.6
Summary: Keplerian system model
Author-email: Jean-Baptiste Delisle <jean-baptiste.delisle@unige.ch>
Project-URL: Homepage, https://gitlab.unige.ch/delisle/kepmodel
Project-URL: Issues, https://gitlab.unige.ch/delisle/kepmodel/-/issues
Classifier: Programming Language :: Python :: 3
Classifier: License :: OSI Approved :: European Union Public Licence 1.2 (EUPL 1.2)
Classifier: Operating System :: OS Independent
Requires-Python: >=3.8
License-File: LICENSE
Requires-Dist: numpy>=1.16
Requires-Dist: scipy>=1.2
Requires-Dist: kepderiv>=1.0.3
Requires-Dist: spleaf>=2.0
